pyqt_crdt/__init__.py
pyqt_crdt/_websocket_provider.py
pyqt_crdt-0.1.0.dist-info/METADATA
pyqt_crdt-0.1.0.dist-info/WHEEL
pyqt_crdt-0.1.0.dist-info/licenses/LICENSE
pyqt_crdt-0.1.0.dist-info/RECORD
