Metadata-Version: 2.4
Name: pyqt-crdt
Version: 0.1.0
Summary: Toolkit and examples for working with Qt and CRDTs in Python
Project-URL: Homepage, https://github.com/davidbrochart/pyqt-crdt
Author-email: David Brochart <david.brochart@gmail.com>
License: Copyright 2025 David Brochart
License-File: LICENSE
Keywords: crdt,qt
Classifier: Development Status :: 4 - Beta
Classifier: Intended Audience :: Developers
Classifier: License :: OSI Approved :: BSD License
Classifier: Programming Language :: Python
Classifier: Programming Language :: Python :: 3.9
Classifier: Programming Language :: Python :: 3.10
Classifier: Programming Language :: Python :: 3.11
Classifier: Programming Language :: Python :: 3.12
Classifier: Programming Language :: Python :: 3.13
Classifier: Programming Language :: Python :: Implementation :: CPython
Classifier: Programming Language :: Python :: Implementation :: PyPy
Classifier: Programming Language :: Rust
Requires-Python: >=3.9
Requires-Dist: pycrdt<0.13.0,>=0.12.8
Provides-Extra: test
Requires-Dist: anyio; extra == 'test'
Requires-Dist: mypy; extra == 'test'
Requires-Dist: pytest<9,>=8.3.4; extra == 'test'
Requires-Dist: trio<0.29,>=0.25.1; extra == 'test'
